db_helper_test4/__init__.py
db_helper_test4/core.py
db_helper_test4/log.py
db_helper_test4/server.py
db_helper_test4-0.1.1.dist-info/METADATA
db_helper_test4-0.1.1.dist-info/WHEEL
db_helper_test4-0.1.1.dist-info/top_level.txt
db_helper_test4-0.1.1.dist-info/RECORD
